htstools/__init__.py
htstools/cli.py
htstools/io.py
htstools/normalize.py
htstools/plot.py
htstools/qc.py
htstools/summarize.py
htstools/tables.py
htstools/utils.py
hts_tools-0.0.4.post2.dist-info/LICENSE
hts_tools-0.0.4.post2.dist-info/METADATA
hts_tools-0.0.4.post2.dist-info/WHEEL
hts_tools-0.0.4.post2.dist-info/entry_points.txt
hts_tools-0.0.4.post2.dist-info/top_level.txt
hts_tools-0.0.4.post2.dist-info/RECORD
