Metadata-Version: 2.1
Name: hts-tools
Version: 0.0.4.post2
Summary: Parsing and analysing platereader absorbance and fluorescence data.
Author-email: Eachan Johnson <eachan.johnson@crick.ac.uk>
License: MIT License
Project-URL: Homepage, https://github.com/scbirlab/hts-tools
Project-URL: Bug Tracker, https://github.com/scbirlab/hts-tools/issues
Keywords: science,assay,platereader,analysis
Classifier: Development Status :: 3 - Alpha
Classifier: Intended Audience :: Science/Research
Classifier: Topic :: Scientific/Engineering :: Bio-Informatics
Classifier: License :: OSI Approved :: MIT License
Classifier: Programming Language :: Python :: 3.9
Classifier: Programming Language :: Python :: 3.10
Classifier: Programming Language :: Python :: 3.11
Classifier: Programming Language :: Python :: 3.12
Classifier: Programming Language :: Python :: 3 :: Only
Requires-Python: >=3.9
License-File: LICENSE
Requires-Dist: carabiner-tools[mpl,pd]>=0.0.3.post1
Requires-Dist: matplotlib
Requires-Dist: numpy
Requires-Dist: openpyxl==3.1.0
Requires-Dist: pandas
Requires-Dist: scipy
